LICENSE
MANIFEST.in
README.md
requirements.txt
setup.py
mlsploit/__init__.py
mlsploit/paths.py
mlsploit/_auxiliary/Dockerfile
mlsploit/_auxiliary/mlsploit_module.schema
mlsploit/_auxiliary/dummy_module/.keep
mlsploit/core/__init__.py
mlsploit/core/base.py
mlsploit/core/job.py
mlsploit/core/module.py
mlsploit/dataset/__init__.py
mlsploit/dataset/datasets.py
mlsploit/dataset/features.py
mlsploit/dataset/base/__init__.py
mlsploit/dataset/base/dataset.py
mlsploit/dataset/base/feature.py
mlsploit/dataset/base/metadata.py
mlsploit_py.egg-info/PKG-INFO
mlsploit_py.egg-info/SOURCES.txt
mlsploit_py.egg-info/dependency_links.txt
mlsploit_py.egg-info/not-zip-safe
mlsploit_py.egg-info/requires.txt
mlsploit_py.egg-info/top_level.txt